openvino/__init__.py
openvino/__init__.pyi
openvino/_op_base.py
openvino/_op_base.pyi
openvino/_ov_api.py
openvino/_ov_api.pyi
openvino/_pyopenvino.cp311-win_amd64.pyd
openvino/exceptions.py
openvino/exceptions.pyi
openvino/package_utils.py
openvino/package_utils.pyi
openvino/_offline_transformations/__init__.py
openvino/_pyopenvino/__init__.pyi
openvino/_pyopenvino/_offline_transformations.pyi
openvino/_pyopenvino/experimental.pyi
openvino/_pyopenvino/frontend.pyi
openvino/_pyopenvino/layout_helpers.pyi
openvino/_pyopenvino/passes.pyi
openvino/_pyopenvino/preprocess.pyi
openvino/_pyopenvino/util.pyi
openvino/_pyopenvino/op/__init__.pyi
openvino/_pyopenvino/op/util.pyi
openvino/_pyopenvino/properties/__init__.pyi
openvino/_pyopenvino/properties/device.pyi
openvino/_pyopenvino/properties/hint.pyi
openvino/_pyopenvino/properties/intel_auto.pyi
openvino/_pyopenvino/properties/intel_cpu.pyi
openvino/_pyopenvino/properties/intel_npu.pyi
openvino/_pyopenvino/properties/log.pyi
openvino/_pyopenvino/properties/streams.pyi
openvino/_pyopenvino/properties/intel_gpu/__init__.pyi
openvino/_pyopenvino/properties/intel_gpu/hint.pyi
openvino/cmake/OpenVINOConfig-version.cmake
openvino/cmake/OpenVINOConfig.cmake
openvino/cmake/OpenVINOTargets-release.cmake
openvino/cmake/OpenVINOTargets.cmake
openvino/cmake/TBBConfig.cmake
openvino/cmake/TBBConfigVersion.cmake
openvino/cmake/TBBTargets-release.cmake
openvino/cmake/TBBTargets.cmake
openvino/experimental/__init__.py
openvino/experimental/__init__.pyi
openvino/frontend/__init__.py
openvino/frontend/__init__.pyi
openvino/frontend/frontend.py
openvino/frontend/frontend.pyi
openvino/frontend/jax/__init__.py
openvino/frontend/jax/jaxpr_decoder.py
openvino/frontend/jax/passes.py
openvino/frontend/jax/py_jax_frontend.cp311-win_amd64.pyd
openvino/frontend/jax/utils.py
openvino/frontend/onnx/__init__.py
openvino/frontend/onnx/py_onnx_frontend.cp311-win_amd64.pyd
openvino/frontend/paddle/__init__.py
openvino-2025.3.0.dist-info/licenses/LICENSE
openvino-2025.3.0.dist-info/licenses/licensing/onednn_third-party-programs.txt
openvino-2025.3.0.dist-info/licenses/licensing/onetbb_third-party-programs.txt
openvino-2025.3.0.dist-info/licenses/licensing/runtime-third-party-programs.txt
openvino-2025.3.0.dist-info/METADATA
openvino-2025.3.0.dist-info/WHEEL
openvino-2025.3.0.dist-info/entry_points.txt
openvino-2025.3.0.dist-info/top_level.txt
openvino-2025.3.0.dist-info/RECORD
