Metadata-Version: 2.4
Name: openvino
Version: 2025.3.0
Summary: OpenVINO(TM) Runtime
Home-page: https://docs.openvino.ai/2023.0/index.html
Download-URL: https://github.com/openvinotoolkit/openvino/releases
Author-email: OpenVINO Developers <openvino@intel.com>
License: OSI Approved :: Apache Software License
Classifier: Programming Language :: Python :: 3.9
Classifier: Programming Language :: Python :: 3.10
Classifier: Programming Language :: Python :: 3.11
Classifier: Programming Language :: Python :: 3.12
Classifier: Programming Language :: Python :: 3.13
Requires-Python: >=3.9
License-File: LICENSE
License-File: licensing/runtime-third-party-programs.txt
License-File: licensing/onetbb_third-party-programs.txt
License-File: licensing/onednn_third-party-programs.txt
Requires-Dist: numpy<2.3.0,>=1.16.6
Requires-Dist: openvino-telemetry>=2023.2.1
Requires-Dist: packaging
Dynamic: download-url
Dynamic: home-page
Dynamic: license-file
